locsearch-0.1.2.dist-info/licenses/LICENSE
losearch/__init__.py
losearch/core/__init__.py
losearch/core/accuracy_enhancer.py
losearch/core/engine.py
losearch/core/search_engine.py
losearch/core/speed_optimizer.py
losearch/models/__init__.py
losearch/utils/__init__.py
losearch/utils/context_extractor.py
losearch/utils/text_processor.py
locsearch-0.1.2.dist-info/METADATA
locsearch-0.1.2.dist-info/WHEEL
locsearch-0.1.2.dist-info/top_level.txt
locsearch-0.1.2.dist-info/RECORD
