Metadata-Version: 2.4
Name: LocSearch
Version: 0.1.2
Summary: A high-performance Python search library with intelligent relevance scoring
Author-email: LocSearch Team <team@locsearch.com>
License: MIT
Keywords: search,library,database,indexing,relevance,text-processing
Classifier: Development Status :: 4 - Beta
Classifier: Intended Audience :: Developers
Classifier: Programming Language :: Python :: 3
Classifier: Programming Language :: Python :: 3.9
Classifier: Programming Language :: Python :: 3.10
Classifier: Programming Language :: Python :: 3.11
Classifier: Programming Language :: Python :: 3.12
Classifier: License :: OSI Approved :: MIT License
Classifier: Operating System :: OS Independent
Requires-Python: >=3.9
License-File: LICENSE
Requires-Dist: build>=1.2.2.post1
Requires-Dist: flask>=3.0.3
Requires-Dist: nltk>=3.9.1
Requires-Dist: redis>=6.1.1
Requires-Dist: scikit-learn>=1.3.2
Requires-Dist: sqlalchemy>=2.0.0
Requires-Dist: twine>=6.1.0
Provides-Extra: dev
Requires-Dist: pytest>=7.0.0; extra == "dev"
Requires-Dist: black>=23.0.0; extra == "dev"
Requires-Dist: ruff>=0.1.0; extra == "dev"
Requires-Dist: mypy>=1.0.0; extra == "dev"
Dynamic: license-file
